{
  "2025-01__Annunci su internet": "Marketplace",
  "2025-01__Autoscout24": "Marketplace",
  "2025-01__Cliente Storico": "Walk-in",
  "2025-01__Cliente storico": "Walk-in",
  "2025-01__DEM": "Dem - sms",
  "2025-01__Datasharing Mercedes Benz": "Casa Madre",
  "2025-01__Datasharing Mercedes Benz MBFS": "Casa Madre",
  "2025-01__Facebook": "Social Ads",
  "2025-01__GOOGLE ADS": "Google Ads",
  "2025-01__INVITO EVENTO": "Eventi",
  "2025-01__Instagram": "Social Ads",
  "2025-01__Lead ricevuto da mail: no-reply@stockspark.io": "Sito",
  "2025-01__Marketplace (autoscout - subito)": "Marketplace",
  "2025-01__Mercedes PaCo": "Meta Organico",
  "2025-01__Omoda - 3rd Party": "Casa Madre",
  "2025-01__Omoda - In-store": "Casa Madre",
  "2025-01__Omoda - Official Website": "Casa Madre",
  "2025-01__Omoda - Official Website - G+": "Casa Madre",
  "2025-01__Passaparola": "Walk-in",
  "2025-01__Sito internet Lodauto": "Sito",
  "2025-01__Sito internet e/o web": "Organico",
  "2025-01__Social (Instagram - Facebook)": "Social Ads",
  "2025-01__Subito.it": "Marketplace",
  "2025-01__Walk in": "Walk-in",
  "2025-01__lodauto.it": "Sito",
  "2025-02__Annunci su internet": "Marketplace",
  "2025-02__Automobile.it": "Altro",
  "2025-02__Autoscout24": "Marketplace",
  "2025-02__Cliente Storico": "Walk-in",
  "2025-02__Cliente storico": "Walk-in",
  "2025-02__Facebook": "Meta Organico",
  "2025-02__GOOGLE ADS": "Google Ads",
  "2025-02__Instagram": "Social Ads",
  "2025-02__Lead ricevuto da mail: no-reply@stockspark.io": "Sito",
  "2025-02__Mercedes PaCo": "Casa Madre",
  "2025-02__Omoda - 3rd Party": "Casa Madre",
  "2025-02__Omoda - In-store": "Casa Madre",
  "2025-02__Omoda - Official Website": "Casa Madre",
  "2025-02__Omoda - Official Website - G+": "Casa Madre",
  "2025-02__Passaparola": "Walk-in",
  "2025-02__Sito internet Lodauto": "Sito",
  "2025-02__Sito internet e/o web": "Sito",
  "2025-02__Social (instagram - facebook)": "Social Ads",
  "2025-02__Subito.it": "Marketplace",
  "2025-02__Walk in": "Walk-in",
  "2025-02__lodauto.it": "Sito",
  "2025-02__lodoutlet": "Eventi",
  "2025-03__Annunci su internet": "Marketplace",
  "2025-03__Automobile.it": "Altro",
  "2025-03__Autoscout24": "Marketplace",
  "2025-03__Cliente Storico": "Walk-in",
  "2025-03__Cliente storico": "Walk-in",
  "2025-03__DEM": "Dem - sms",
  "2025-03__Facebook": "Social Ads",
  "2025-03__GOOGLE ADS": "Google Ads",
  "2025-03__LODOUTLET": "Eventi",
  "2025-03__Lead ricevuto da mail: no-reply@stockspark.io": "Sito",
  "2025-03__Marketplace (autoscout - subito)": "Altro",
  "2025-03__Mercedes PaCo": "Casa Madre",
  "2025-03__Omoda - In-store": "Casa Madre",
  "2025-03__Omoda - Official Website": "Casa Madre",
  "2025-03__Omoda - Official Website - G+": "Casa Madre",
  "2025-03__Passaparola": "Walk-in",
  "2025-03__Sito internet Lodauto": "Altro",
  "2025-03__Sito internet e/o web": "Sito",
  "2025-03__Social (instagram - facebook)": "Social Ads",
  "2025-03__Subito.it": "Marketplace",
  "2025-03__Walk in": "Walk-in",
  "2025-03__lodauto.it": "Sito",
  "2025-04__Annunci su internet": "Marketplace",
  "2025-04__Automobile.it": "Altro",
  "2025-04__Autoscout24": "Marketplace",
  "2025-04__Banner": "Social Ads",
  "2025-04__Cliente Storico": "Walk-in",
  "2025-04__DEM": "Dem - sms",
  "2025-04__Datasharing Mercedes Benz MBFS": "Casa Madre",
  "2025-04__Facebook": "Social Ads",
  "2025-04__GOOGLE ADS": "Google Ads",
  "2025-04__Lead ricevuto da mail: no-reply@stockspark.io": "Sito",
  "2025-04__Mercedes PaCo": "Casa Madre",
  "2025-04__Omoda - In-store": "Casa Madre",
  "2025-04__Omoda - Official Website": "Casa Madre",
  "2025-04__Omoda - Official Website - DriveK": "Casa Madre",
  "2025-04__Passaparola": "Walk-in",
  "2025-04__Sito internet Lodauto": "Sito",
  "2025-04__Sito internet e/o web": "Sito",
  "2025-04__Social (instagram - facebook)": "Altro",
  "2025-04__Subito.it": "Marketplace",
  "2025-04__Walk in": "Walk-in",
  "2025-04__lodauto.it": "Sito",
  "2025-05__Annunci su internet": "Marketplace",
  "2025-05__Automobile.it": "Altro",
  "2025-05__Autoscout24": "Marketplace",
  "2025-05__CRAZY DAYS": "Eventi",
  "2025-05__Campagna Adv F": "Social Ads",
  "2025-05__Campagna Adv I": "Social Ads",
  "2025-05__Cliente Storico": "Walk-in",
  "2025-05__DEM": "Dem - sms",
  "2025-05__Datasharing Mercedes Benz": "Casa Madre",
  "2025-05__Datasharing Mercedes Benz MBFS": "Casa Madre",
  "2025-05__Facebook": "Social Ads",
  "2025-05__GOOGLE ADS": "Google Ads",
  "2025-05__Glytter": "Social Ads",
  "2025-05__Instagram": "Altro",
  "2025-05__Lead ricevuto da mail: no-reply@stockspark.io": "Sito",
  "2025-05__Mercedes PaCo": "Casa Madre",
  "2025-05__Omoda - Call Center - Call Center": "Casa Madre",
  "2025-05__Omoda - In-store": "Casa Madre",
  "2025-05__Omoda - Official Website": "Casa Madre",
  "2025-05__Omoda - Official Website - DriveK": "Casa Madre",
  "2025-05__Omoda - Official Website - G+": "Casa Madre",
  "2025-05__Passaparola": "Walk-in",
  "2025-05__Sito internet Lodauto": "Sito",
  "2025-05__Sito internet e/o web": "Sito",
  "2025-05__Social (Instagram - Facebook)": "Social Ads",
  "2025-05__Social (instagram - facebook)": "Marketplace",
  "2025-05__Subito.it": "Marketplace",
  "2025-05__Walk in": "Walk-in",
  "2025-05__lodauto.it": "Sito",
  "2025-06__Automobile.it": "Altro",
  "2025-06__Autoscout24": "Marketplace",
  "2025-06__Banner": "Altro",
  "2025-06__CRAZY DAYS": "Eventi",
  "2025-06__CSI": "Altro",
  "2025-06__CSI OFFICINA": "Altro",
  "2025-06__Campagna Adv F": "Social Ads",
  "2025-06__Campagna Adv I": "Social Ads",
  "2025-06__Cliente Storico": "Walk-in",
  "2025-06__DEM": "Dem - sms",
  "2025-06__Datasharing Mercedes Benz": "Casa Madre",
  "2025-06__GOOGLE ADS": "Google Ads",
  "2025-06__Glytter": "Social Ads",
  "2025-06__JAECOO - Official Website": "Casa Madre",
  "2025-06__JAECOO - Official Website - G+": "Casa Madre",
  "2025-06__Lead ricevuto da mail: no-reply@stockspark.io": "Sito",
  "2025-06__Mercedes PaCo": "Casa Madre",
  "2025-06__OMODA - Official Website": "Casa Madre",
  "2025-06__OMODA - Official Website - G+": "Casa Madre",
  "2025-06__Omoda - In-store": "Casa Madre",
  "2025-06__Omoda - Official Website": "Casa Madre",
  "2025-06__Passaparola": "Walk-in",
  "2025-06__Sito internet Lodauto": "Sito",
  "2025-06__Sito internet e/o web": "Sito",
  "2025-06__Social (instagram - facebook)": "Social Ads",
  "2025-06__Subito.it": "Marketplace",
  "2025-06__Walk in": "Walk-in",
  "2025-06__estrazione usato": "Altro",
  "2025-06__lodauto.it": "Sito",
  "2025-07__Annunci su internet": "Marketplace",
  "2025-07__Automobile.it": "Altro",
  "2025-07__Autoscout24": "Marketplace",
  "2025-07__Banner": "Social Ads",
  "2025-07__Campagna Adv F": "Social Ads",
  "2025-07__Cliente Storico": "Walk-in",
  "2025-07__Cliente storico": "Walk-in",
  "2025-07__Cross Sell Officina": "Altro",
  "2025-07__DealerK": "Sito",
  "2025-07__Facebook": "Social Ads",
  "2025-07__GOOGLE ADS": "Google Ads",
  "2025-07__JAECOO - Official Website": "Casa Madre",
  "2025-07__JAECOO - Official Website - G+": "Casa Madre",
  "2025-07__Lead ricevuto da mail: no-reply@stockspark.io": "Sito",
  "2025-07__Mercedes PaCo": "Casa Madre",
  "2025-07__OMODA - Official Website": "Casa Madre",
  "2025-07__OMODA - Official Website - G+": "Casa Madre",
  "2025-07__Omoda - In-store": "Casa Madre",
  "2025-07__Passaparola": "Walk-in",
  "2025-07__Sito internet Lodauto": "Sito",
  "2025-07__Sito internet e/o web": "Organico",
  "2025-07__Social (instagram - facebook)": "Social Ads",
  "2025-07__Subito.it": "Marketplace",
  "2025-07__Walk in": "Walk-in",
  "2025-07__lodauto.it": "Sito",
  "2025-08__Annunci su internet": "Marketplace",
  "2025-08__Automobile.it": "Altro",
  "2025-08__Autoscout24": "Marketplace",
  "2025-08__Banner": "Altro",
  "2025-08__Campagna Adv F": "Social Ads",
  "2025-08__Cliente Storico": "Walk-in",
  "2025-08__Cross Sell Officina": "Organico",
  "2025-08__Facebook": "Altro",
  "2025-08__GOOGLE ADS": "Google Ads",
  "2025-08__Glytter": "Sito",
  "2025-08__JAECOO - Official Website": "Casa Madre",
  "2025-08__JAECOO - Official Website - G+": "Casa Madre",
  "2025-08__Lead ricevuto da mail: no-reply@stockspark.io": "Sito",
  "2025-08__Mercedes PaCo": "Casa Madre",
  "2025-08__OMODA - Official Website": "Casa Madre",
  "2025-08__OMODA - Official Website - G+": "Casa Madre",
  "2025-08__Passaparola": "Walk-in",
  "2025-08__Sito internet Lodauto": "Altro",
  "2025-08__Sito internet e/o web": "Sito",
  "2025-08__Subito.it": "Marketplace",
  "2025-08__Walk in": "Walk-in",
  "2025-08__lodauto.it": "Sito",
  "2025-09__Annunci su internet": "Social Ads",
  "2025-09__Automobile.it": "Altro",
  "2025-09__Autoscout24": "Marketplace",
  "2025-09__Banner": "Altro",
  "2025-09__Campagna Adv F": "Social Ads",
  "2025-09__Cliente Storico": "Walk-in",
  "2025-09__Cliente storico": "Altro",
  "2025-09__Cross Sell Officina": "Altro",
  "2025-09__DEM": "Dem - sms",
  "2025-09__DealerK": "Altro",
  "2025-09__Dem": "Dem - sms",
  "2025-09__Facebook": "Social Ads",
  "2025-09__GOOGLE ADS": "Google Ads",
  "2025-09__Instagram": "Altro",
  "2025-09__JAECOO - Official Website": "Altro",
  "2025-09__JAECOO - Official Website - G+": "Altro",
  "2025-09__Lead ricevuto da mail: no-reply@stockspark.io": "Sito",
  "2025-09__Lead ricevuto da mail: noreply@iovox.com": "Marketplace",
  "2025-09__Mercedes PaCo": "Casa Madre",
  "2025-09__OMODA - Official Website": "Altro",
  "2025-09__OMODA - Official Website - G+": "Altro",
  "2025-09__Omoda - In-store": "Altro",
  "2025-09__Passaparola": "Walk-in",
  "2025-09__Sito internet Lodauto": "Sito",
  "2025-09__Sito internet e/o web": "Marketplace",
  "2025-09__Social (instagram - facebook)": "Social Ads",
  "2025-09__Subito.it": "Marketplace",
  "2025-09__Walk in": "Walk-in",
  "2025-09__lodauto.it": "Sito",
  "2025-10__Annunci su internet": "Marketplace",
  "2025-10__Automobile.it": "Altro",
  "2025-10__Autoscout24": "Marketplace",
  "2025-10__Banner": "Altro",
  "2025-10__Campagna Adv F": "Social Ads",
  "2025-10__Cliente Storico": "Walk-in",
  "2025-10__Cliente storico": "Walk-in",
  "2025-10__Cross Sell Officina": "Altro",
  "2025-10__DealerK": "Altro",
  "2025-10__Facebook": "Altro",
  "2025-10__GOOGLE ADS": "Google Ads",
  "2025-10__Glytter": "Altro",
  "2025-10__Instagram": "Meta Organico",
  "2025-10__JAECOO - In-store": "Altro",
  "2025-10__JAECOO - Official Website": "Altro",
  "2025-10__JAECOO - Official Website - G+": "Altro",
  "2025-10__Lead ricevuto da mail: no-reply@stockspark.io": "Altro",
  "2025-10__Lead ricevuto da mail: noreply@iovox.com": "Sito",
  "2025-10__Mercedes PaCo": "Marketplace",
  "2025-10__OMODA - Official Website": "Altro",
  "2025-10__OMODA - Official Website - G+": "Altro",
  "2025-10__Omoda - In-store": "Altro",
  "2025-10__PROMO AZIENDE": "Altro",
  "2025-10__Passaparola": "Walk-in",
  "2025-10__Sito internet Lodauto": "Sito",
  "2025-10__Sito internet e/o web": "Sito",
  "2025-10__Social (instagram - facebook)": "Altro",
  "2025-10__Subito.it": "Walk-in",
  "2025-10__Walk in": "Walk-in",
  "2025-10__lodauto.it": "Altro",
  "2025-11__Annunci su internet": "Marketplace",
  "2025-11__Automobile.it": "Altro",
  "2025-11__Autoscout24": "Marketplace",
  "2025-11__Campagna Adv F": "Social Ads",
  "2025-11__Campagna Adv I": "Social Ads",
  "2025-11__Cliente Storico": "Walk-in",
  "2025-11__Cliente storico": "Walk-in",
  "2025-11__Cross Sell Officina": "Organico",
  "2025-11__DEM": "Dem - sms",
  "2025-11__DealerK": "Altro",
  "2025-11__GOOGLE ADS": "Google Ads",
  "2025-11__Instagram": "Meta Organico",
  "2025-11__JAECOO - Official Website": "Altro",
  "2025-11__JAECOO - Official Website - G+": "Altro",
  "2025-11__Lead ricevuto da mail: no-reply@stockspark.io": "Sito",
  "2025-11__Marketplace (autoscout - subito)": "Altro",
  "2025-11__Mercedes PaCo": "Casa Madre",
  "2025-11__OMODA - Official Website": "Altro",
  "2025-11__OMODA - Official Website - G+": "Altro",
  "2025-11__Omoda - In-store": "Altro",
  "2025-11__PROMO AZIENDE": "Altro",
  "2025-11__Passaparola": "Walk-in",
  "2025-11__Sito internet Lodauto": "Organico",
  "2025-11__Sito internet e/o web": "Sito",
  "2025-11__Social (Instagram - Facebook)": "Social Ads",
  "2025-11__Social (instagram - facebook)": "Social Ads",
  "2025-11__Subito.it": "Marketplace",
  "2025-11__Walk in": "Walk-in",
  "2025-11__lodauto.it": "Sito"
}